pmr_elirobots_msgs/__init__.py
pmr_elirobots_msgs/cmd.py
pmr_elirobots_msgs/header.py
pmr_elirobots_msgs/py.typed
pmr_elirobots_msgs/types.py
pmr_elirobots_msgs-0.0.3.dist-info/METADATA
pmr_elirobots_msgs-0.0.3.dist-info/WHEEL
pmr_elirobots_msgs-0.0.3.dist-info/RECORD
