Metadata-Version: 2.4
Name: pmr-elirobots-msgs
Version: 0.0.3
Summary: 
License-Expression: MIT
Author: Felipe Gomes de Melo D'Elia
Author-email: felipegmelo@usp.br
Requires-Python: >=3.10
Classifier: Programming Language :: Python :: 3
Classifier: Programming Language :: Python :: 3.10
Classifier: Programming Language :: Python :: 3.11
Classifier: Programming Language :: Python :: 3.12
Classifier: Programming Language :: Python :: 3.13
Classifier: Programming Language :: Python :: 3.14
Requires-Dist: dataclasses-json
Requires-Dist: pydantic
